kafka_mcp_server/__init__.py
kafka_mcp_server/kafka.py
kafka_mcp_server/server.py
kafka_mcp_server/settings.py
kafka_mcp_server-0.1.1.dist-info/licenses/LICENSE
kafka_mcp_server-0.1.1.dist-info/METADATA
kafka_mcp_server-0.1.1.dist-info/WHEEL
kafka_mcp_server-0.1.1.dist-info/entry_points.txt
kafka_mcp_server-0.1.1.dist-info/top_level.txt
kafka_mcp_server-0.1.1.dist-info/RECORD
