Metadata-Version: 2.4
Name: kafka-mcp-server
Version: 0.1.1
Summary: Add your description here
Requires-Python: >=3.13
License-File: LICENSE
Requires-Dist: aiokafka>=0.12.0
Requires-Dist: mcp[cli]>=1.6.0
Requires-Dist: pydantic>=2.10.6
Requires-Dist: pydantic-settings~=2.8.1
Requires-Dist: python-dotenv>=1.1.0
Dynamic: license-file
